adventcalendartui_xvcf/__init__.py
adventcalendartui_xvcf/main.py
adventcalendartui_xvcf-0.0.1.dist-info/METADATA
adventcalendartui_xvcf-0.0.1.dist-info/WHEEL
adventcalendartui_xvcf-0.0.1.dist-info/entry_points.txt
adventcalendartui_xvcf-0.0.1.dist-info/licenses/LICENSE
adventcalendartui_xvcf-0.0.1.dist-info/RECORD
