Metadata-Version: 2.4
Name: adventcalendartui_xvcf
Version: 0.0.1
License-File: LICENSE
Requires-Dist: textual
